LICENSE
MANIFEST.in
pyproject.toml
setup.py
CacheRequests/__init__.py
CacheRequests/cloudscraper.py
CacheRequests/path.py
CacheRequests/py.typed
CacheRequests/response.py
CacheRequests/session.py
CacheRequests/session.pyi
CacheRequests/urlmap.py
CacheRequests/utils.py
PersistentRequests.egg-info/PKG-INFO
PersistentRequests.egg-info/SOURCES.txt
PersistentRequests.egg-info/dependency_links.txt
PersistentRequests.egg-info/requires.txt
PersistentRequests.egg-info/top_level.txt