Metadata-Version: 2.1
Name: PersistentRequests
Version: 0.1.3
Summary: A Python library that provides a simple and effective caching layer for web requests.
Home-page: https://github.com/thefcraft/CacheRequests
Author: ThefCraft
Author-email: sisodiyalaksh@gmail.com
License: UNKNOWN
Platform: UNKNOWN
Classifier: Programming Language :: Python :: 3
Classifier: License :: OSI Approved :: MIT License
Classifier: Operating System :: OS Independent
License-File: LICENSE
